ddmail_e2e_testing/__init__.py
ddmail_e2e_testing/__main__.py
ddmail_e2e_testing/helpers.py
ddmail_e2e_testing/test_auth.py
ddmail_e2e_testing/test_email.py
ddmail_e2e_testing/test_openpgp.py
ddmail_e2e_testing-0.0.1.dist-info/METADATA
ddmail_e2e_testing-0.0.1.dist-info/WHEEL
ddmail_e2e_testing-0.0.1.dist-info/entry_points.txt
ddmail_e2e_testing-0.0.1.dist-info/licenses/LICENSE
ddmail_e2e_testing-0.0.1.dist-info/RECORD
