Metadata-Version: 2.4
Name: ddmail_e2e_testing
Version: 0.0.1
Summary: End-to-end testing for the DDMail project.
Project-URL: Homepage, https://github.com/drzobin/ddmail_e2e_testing
Project-URL: Issues, https://github.com/drzobin/ddmail_e2e_testing/issues
Author-email: Robin Larsson <me@drz.se>
License-Expression: AGPL-3.0
License-File: LICENSE
Classifier: Operating System :: POSIX :: Linux
Classifier: Programming Language :: Python :: 3
Requires-Python: >=3.8
Requires-Dist: pytest
Requires-Dist: python-gnupg
Requires-Dist: requests
Requires-Dist: toml
Provides-Extra: dev
Requires-Dist: flake8; extra == 'dev'
Requires-Dist: hatchling; extra == 'dev'
Requires-Dist: pytest; extra == 'dev'
Requires-Dist: python-gnupg; extra == 'dev'
Requires-Dist: requests; extra == 'dev'
Requires-Dist: toml; extra == 'dev'
Requires-Dist: twine; extra == 'dev'
Provides-Extra: test
Requires-Dist: flake8; extra == 'test'
Requires-Dist: pytest; extra == 'test'
Requires-Dist: python-gnupg; extra == 'test'
Requires-Dist: requests; extra == 'test'
Requires-Dist: toml; extra == 'test'
